<?xml version="1.0" encoding="UTF-8"?>
<metadata xml:lang="en"><Esri><CreaDate>20221231</CreaDate><CreaTime>11004200</CreaTime><ArcGISFormat>1.0</ArcGISFormat><SyncOnce>TRUE</SyncOnce><DataProperties><lineage><Process ToolSource="c:\program files (x86)\arcgis\desktop10.8\ArcToolbox\Toolboxes\Data Management Tools.tbx\CalculateField" Date="20221231" Time="110042">CalculateField Projected_Acute_Mal fg [pro] VB #</Process><Process ToolSource="c:\program files (x86)\arcgis\desktop10.8\ArcToolbox\Toolboxes\Data Management Tools.tbx\CalculateField" Date="20221231" Time="112147">CalculateField Projected_Acute_Mal curr [pro] VB #</Process><Process ToolSource="c:\program files (x86)\arcgis\desktop10.8\ArcToolbox\Toolboxes\Data Management Tools.tbx\CalculateField" Date="20221231" Time="112157">CalculateField Projected_Acute_Mal projj [pro] VB #</Process><Process ToolSource="c:\program files (x86)\arcgis\desktop10.8\ArcToolbox\Toolboxes\Data Management Tools.tbx\CalculateField" Date="20221231" Time="112808">CalculateField Projected_Acute_Mal sd [curr] VB #</Process></lineage></DataProperties></Esri></metadata>
